LICENSE.txt
README.md
pyproject.toml
setup.py
src/experiment_config.egg-info/PKG-INFO
src/experiment_config.egg-info/SOURCES.txt
src/experiment_config.egg-info/dependency_links.txt
src/experiment_config.egg-info/requires.txt
src/experiment_config.egg-info/top_level.txt
src/expfig/__init__.py
src/expfig/fig.py
src/expfig/namespacify.py
src/expfig/core/__init__.py
src/expfig/core/_flatten.py
src/expfig/core/_parse.py
src/expfig/core/_parse_yaml_obj.py
src/expfig/core/_str_types.py
src/expfig/core/similar_args.py
src/expfig/functions/__init__.py
src/expfig/functions/comparison.py
src/expfig/goodybag/__init__.py
src/expfig/goodybag/figure_tracker.py
src/expfig/goodybag/running_mean_std.py
src/expfig/logging/__init__.py
src/expfig/logging/log_dir.py
src/expfig/logging/logger.py
src/expfig/logging/tape_recorder.py
src/expfig/utils/__init__.py
src/expfig/utils/api.py
src/expfig/utils/dependencies.py
tests/test_parse.py
tests/test_yaml_type.py