Metadata-Version: 2.1
Name: experiment-config
Version: 1.0.4
Summary: A yaml-based configuration for reproducible python experiments.
Maintainer: Avishai Halev
Maintainer-email: avishaihalev@gmail.com
License: MIT License
Project-URL: Source Code, https://github.com/ahalev/experiment-config/tree/v1.0.4
Requires-Python: >=3.6
Provides-Extra: dev
Provides-Extra: pandas
Provides-Extra: all
License-File: LICENSE.txt
